odoo/addons/product_form_sale_link/README.rst
odoo/addons/product_form_sale_link/__init__.py
odoo/addons/product_form_sale_link/__manifest__.py
odoo/addons/product_form_sale_link/i18n/ca.po
odoo/addons/product_form_sale_link/i18n/es.po
odoo/addons/product_form_sale_link/i18n/fr.po
odoo/addons/product_form_sale_link/i18n/nb.po
odoo/addons/product_form_sale_link/i18n/nb_NO.po
odoo/addons/product_form_sale_link/i18n/product_form_sale_link.pot
odoo/addons/product_form_sale_link/models/__init__.py
odoo/addons/product_form_sale_link/models/product_product.py
odoo/addons/product_form_sale_link/models/product_template.py
odoo/addons/product_form_sale_link/readme/CONTRIBUTORS.rst
odoo/addons/product_form_sale_link/readme/DESCRIPTION.rst
odoo/addons/product_form_sale_link/readme/USAGE.rst
odoo/addons/product_form_sale_link/static/description/icon.png
odoo/addons/product_form_sale_link/static/description/index.html
odoo/addons/product_form_sale_link/static/description/product_sale.png
odoo/addons/product_form_sale_link/views/product_product.xml
odoo/addons/product_form_sale_link/views/product_template.xml
odoo/addons/product_form_sale_link/views/sale_order_line.xml
odoo13_addon_product_form_sale_link-13.0.1.1.0.dist-info/METADATA
odoo13_addon_product_form_sale_link-13.0.1.1.0.dist-info/WHEEL
odoo13_addon_product_form_sale_link-13.0.1.1.0.dist-info/top_level.txt
odoo13_addon_product_form_sale_link-13.0.1.1.0.dist-info/RECORD
